{
  "info": {
    "_postman_id": "d6f00ff3-e8b0-4450-b0fa-ad471c661bba",
    "name": "PiedraAzul-Sync-Appointments",
    "schema": "https://schema.getpostman.com/json/collection/v2.1.0/collection.json"
  },
  "item": [
    {
      "name": "Agendar Cita",
      "request": {
        "method": "POST",
        "header": [
          {
            "key": "Content-Type",
            "value": "application/json"
          }
        ],
        "body": {
          "mode": "raw",
          "raw": "{\n  \"patientId\": 1,\n  \"professionalId\": 2,\n  \"appointmentTime\": \"2026-05-10T10:00:00\"\n}"
        },
        "url": {
          "raw": "http://localhost:8080/api/appointments",
          "protocol": "http",
          "host": [
            "localhost"
          ],
          "port": "8080",
          "path": [
            "api",
            "appointments"
          ]
        }
      },
      "response": []
    },
    {
      "name": "Cancelar Cita",
      "request": {
        "method": "POST",
        "header": [],
        "url": {
          "raw": "http://localhost:8080/api/appointments/1/cancel",
          "protocol": "http",
          "host": [
            "localhost"
          ],
          "port": "8080",
          "path": [
            "api",
            "appointments",
            "1",
            "cancel"
          ]
        }
      },
      "response": []
    }
  ]
}